odoo/addons/base_sequence_default/README.rst
odoo/addons/base_sequence_default/__init__.py
odoo/addons/base_sequence_default/__manifest__.py
odoo/addons/base_sequence_default/demo/ir_sequence_demo.xml
odoo/addons/base_sequence_default/i18n/base_sequence_default.pot
odoo/addons/base_sequence_default/i18n/es.po
odoo/addons/base_sequence_default/i18n/it.po
odoo/addons/base_sequence_default/models/__init__.py
odoo/addons/base_sequence_default/models/base.py
odoo/addons/base_sequence_default/readme/CONFIGURE.md
odoo/addons/base_sequence_default/readme/CONTRIBUTORS.md
odoo/addons/base_sequence_default/readme/DESCRIPTION.md
odoo/addons/base_sequence_default/readme/USAGE.md
odoo/addons/base_sequence_default/static/description/icon.png
odoo/addons/base_sequence_default/static/description/index.html
odoo/addons/base_sequence_default/tests/__init__.py
odoo/addons/base_sequence_default/tests/test_project_project.py
odoo_addon_base_sequence_default-16.0.1.0.2.4.dist-info/METADATA
odoo_addon_base_sequence_default-16.0.1.0.2.4.dist-info/WHEEL
odoo_addon_base_sequence_default-16.0.1.0.2.4.dist-info/top_level.txt
odoo_addon_base_sequence_default-16.0.1.0.2.4.dist-info/RECORD
